ulog2kml/__init__.py
ulog2kml/__main__.py
ulog2kml/ulog.py
ulog2kml/ulog2kml.py
ulog2kml-1.0.8.dist-info/LICENSE
ulog2kml-1.0.8.dist-info/METADATA
ulog2kml-1.0.8.dist-info/WHEEL
ulog2kml-1.0.8.dist-info/entry_points.txt
ulog2kml-1.0.8.dist-info/top_level.txt
ulog2kml-1.0.8.dist-info/RECORD
