Metadata-Version: 2.1
Name: ulog2kml
Version: 1.0.8
Summary: A command line program for converting ULog files into time-aware KML files.
Home-page: https://github.com/caseyslaught/ulog2kml
License: MIT
Keywords: ulog kml drone
Platform: UNKNOWN
Classifier: Development Status :: 3 - Alpha
Classifier: Intended Audience :: Developers
Classifier: Programming Language :: Python :: 3
Classifier: License :: OSI Approved :: MIT License
Classifier: Operating System :: OS Independent
Requires-Python: >=3.5
Requires-Dist: numpy (>=1.19.5)
Requires-Dist: simplekml (>=1.3.5)
